nlr_reveal-0.2.2.dist-info/licenses/LICENSE
reVeal/__init__.py
reVeal/_version.py
reVeal/dataframe.py
reVeal/errors.py
reVeal/fileio.py
reVeal/grid.py
reVeal/load.py
reVeal/log.py
reVeal/normalization.py
reVeal/overlay.py
reVeal/cli/__init__.py
reVeal/cli/characterize.py
reVeal/cli/cli.py
reVeal/cli/downscale.py
reVeal/cli/normalize.py
reVeal/cli/score_weighted.py
reVeal/config/__init__.py
reVeal/config/characterize.py
reVeal/config/config.py
reVeal/config/downscale.py
reVeal/config/normalize.py
reVeal/config/score_weighted.py
nlr_reveal-0.2.2.dist-info/METADATA
nlr_reveal-0.2.2.dist-info/WHEEL
nlr_reveal-0.2.2.dist-info/entry_points.txt
nlr_reveal-0.2.2.dist-info/top_level.txt
nlr_reveal-0.2.2.dist-info/RECORD
