Metadata-Version: 2.4
Name: NLR-reVeal
Version: 0.2.2
Summary: The reV Extension for Analyzing Large Loads.
Author-email: Michael Gleason <mike.gleason@nrel.gov>
Maintainer-email: Pavlo Pinchuk <ppinchuk@nrel.gov>
License-Expression: BSD-3-Clause
Project-URL: homepage, https://github.com/NREL/reVeal
Project-URL: documentation, https://nrel.github.io/reVeal/
Project-URL: repository, https://github.com/NREL/reVeal
Keywords: reVeal,NLR,Load Analysis,Geospatial,Site-Suitability
Classifier: Development Status :: 4 - Beta
Classifier: Intended Audience :: Science/Research
Classifier: Natural Language :: English
Classifier: Operating System :: OS Independent
Classifier: Programming Language :: Python :: 3
Classifier: Programming Language :: Python :: 3.12
Classifier: Programming Language :: Python :: 3.13
Classifier: Topic :: Software Development :: Libraries :: Application Frameworks
Requires-Python: >=3.12
License-File: LICENSE
Requires-Dist: exactextract<0.4,>=0.3.0
Requires-Dist: geopandas<2,>=1.1.1
Requires-Dist: gdal<4,>=3.12.1
Requires-Dist: libpysal<5,>=4.13.0
Requires-Dist: nrel-gaps<0.9,>=0.8.11
Requires-Dist: nrel-rex<1,>=0.4.3
Requires-Dist: pandas<3,>=2.3.3
Requires-Dist: pyarrow<23,>=22.0.0
Requires-Dist: pydantic<3,>=2.12.5
Requires-Dist: pyogrio<0.13,>=0.12.1
Requires-Dist: rasterio<2,>=1.4.4
Requires-Dist: tqdm<5,>=4.67.1
Provides-Extra: dev
Requires-Dist: jupyter<1.1,>=1.0.0; extra == "dev"
Requires-Dist: pipreqs<0.5,>=0.4.13; extra == "dev"
Requires-Dist: ruff<0.15,>=0.14.5; extra == "dev"
Requires-Dist: ruff-lsp<0.0.63,>=0.0.62; extra == "dev"
Provides-Extra: test
Requires-Dist: flaky<4,>=3.8.1; extra == "test"
Requires-Dist: pytest<10,>=9.0.1; extra == "test"
Requires-Dist: pytest-cases<4,>=3.9.1; extra == "test"
Requires-Dist: pytest-cov<8,>=7.0.0; extra == "test"
Requires-Dist: pytest-mock<4,>=3.15.1; extra == "test"
Requires-Dist: pytest-profiling<2,>=1.8.1; extra == "test"
Requires-Dist: pytest-xdist<4,>=3.8.0; extra == "test"
Requires-Dist: snakeviz<3,>=2.2.2; extra == "test"
Requires-Dist: tox<5,>=4.32.0; extra == "test"
Provides-Extra: doc
Requires-Dist: ghp-import<3,>=2.1.0; extra == "doc"
Requires-Dist: pydata-sphinx-theme<0.17,>=0.16.1; extra == "doc"
Requires-Dist: sphinx-click<7,>=6.0.0; extra == "doc"
Requires-Dist: sphinx-copybutton<0.6,>=0.5.2; extra == "doc"
Requires-Dist: sphinx-tabs<4,>=3.4.1; extra == "doc"
Requires-Dist: sphinxcontrib-mermaid<2,>=1.0.0; extra == "doc"
Provides-Extra: build
Requires-Dist: build<2,>=1.2.2; extra == "build"
Requires-Dist: pkginfo<2,>=1.12.1.2; extra == "build"
Dynamic: license-file
